{
    "jogos": [
        {
            "nome": "SpongeBob SquarePants: SuperSponge",
            "tags": "SpongeBob SquarePants: SuperSponge bob esponja bope esponcha sony ps1 playstation 1",
            "console": "PlayStation 1 (PS1)",
            "consigla": "ps1",
            "curto": "bob"
        },
        {
            "nome": "Assault: Retribution",
            "tags": "Assault: Retribution sony ps1 playstation 1",
            "console": "PlayStation 1 (PS1)",
            "consigla": "ps1",
            "curto": "assault"
        },
        {
            "nome": "Spider-Man 2: Enter: Electro",
            "tags": "Spider-Man 2: Enter: Electro Spider Man 2 Enter Electro homem aranha miranha sony ps1 playstation 1",
            "console": "PlayStation 1 (PS1)",
            "consigla": "ps1",
            "curto": "miranha"
        },
        {
            "nome": "The Lost World: Jurassic Park",
            "tags": "The Lost World: Jurassic Park The Lost World Jurassic Park dino dinossauro sony ps1 playstation 1",
            "console": "PlayStation 1 (PS1)",
            "consigla": "ps1",
            "curto": "jurassic"
        },
        {
            "nome": "Disruptor",
            "tags": "Disruptor sony ps1 playstation 1",
            "console": "PlayStation 1 (PS1)",
            "consigla": "ps1",
            "curto": "disruptor"
        },
        {
            "nome": "T'ai Fu Wrath of the Tiger",
            "tags": "T'ai Fu Wrath of the Tiger Tai Fu Wrath of the Tiger taifu sony ps1 playstation 1",
            "console": "PlayStation 1 (PS1)",
            "consigla": "ps1",
            "curto": "taifu"
        },
        {
            "nome": "Disney's Donald Duck: Goin' Quackers",
            "tags": "Disney's Donald Duck: Goin' Quackers pato donald sony ps1 playstation 1",
            "console": "PlayStation 1 (PS1)",
            "consigla": "ps1",
            "curto": "donald"
        },
        {
            "nome": "Moto Racer",
            "tags": "Moto Racer sony ps1 playstation 1",
            "console": "PlayStation 1 (PS1)",
            "consigla": "ps1",
            "curto": "moto"
        },
        {
            "nome": "Nightmare Creatures",
            "tags": "Nightmare Creatures sony ps1 playstation 1",
            "console": "PlayStation 1 (PS1)",
            "consigla": "ps1",
            "curto": "nightmare"
        },
        {
            "nome": "Metal Slug X",
            "tags": "Metal Slug X sony ps1 playstation 1",
            "console": "PlayStation 1 (PS1)",
            "consigla": "ps1",
            "curto": "slugx"
        },
        {
            "nome": "Sonic The Hedgehog",
            "tags": "Sonic The Hedgehog 1 Sonic 1 sega mega drive sega genesis",
            "console": "Mega Drive (MD)",
            "consigla": "md",
            "curto": "sonic1"
        },
        {
            "nome": "QuackShot",
            "tags": "QuackShot Starring Donald Duck disney pato donald sega mega drive sega genesis",
            "console": "Mega Drive (MD)",
            "consigla": "md",
            "curto": "quackshot"
        },
        {
            "nome": "Zero Tolerance",
            "tags": "Zero Tolerance sega mega drive sega genesis",
            "console": "Mega Drive (MD)",
            "consigla": "md",
            "curto": "zerotol"
        },
        {
            "nome": "Socket",
            "tags": "Socket tipo sonic soniclike sega mega drive sega genesis",
            "console": "Mega Drive (MD)",
            "consigla": "md",
            "curto": "socket"
        },
        {
            "nome": "Light Crusader",
            "tags": "Light Crusader action rpg de a칞칚o sega mega drive sega genesis",
            "console": "Mega Drive (MD)",
            "consigla": "md",
            "curto": "crusader"
        },
        {
            "nome": "Ice Climber",
            "tags": "Ice Climber nes nintendo",
            "console": "Nintendo (NES)",
            "consigla": "nes",
            "curto": "climber"
        },
        {
            "nome": "Adventure Island",
            "tags": "Adventure Island nes nintendo",
            "console": "Nintendo (NES)",
            "consigla": "nes",
            "curto": "advisland"
        },
        {
            "nome": "Gun.Smoke",
            "tags": "Gun.Smoke nes nintendo",
            "console": "Nintendo (NES)",
            "consigla": "nes",
            "curto": "gunsmoke"
        },
        {
            "nome": "DuckTales",
            "tags": "DuckTales disney Scrooge McDuck Tio Patinhas McPato nes nintendo",
            "console": "Nintendo (NES)",
            "consigla": "nes",
            "curto": "ducktales"
        },
        {
            "nome": "Jackal",
            "tags": "Jackal nes nintendo",
            "console": "Nintendo (NES)",
            "consigla": "nes",
            "curto": "jackal"
        },
        {
            "nome": "Super Mario 64",
            "tags": "Super Mario 64 n64 nintendo 64",
            "console": "Nintendo 64 (N64)",
            "consigla": "n64",
            "curto": "mario64"
        },
        {
            "nome": "Castlevania: Legacy of Darkness",
            "tags": "Castlevania: Legacy of Darkness n64 nintendo 64",
            "console": "Nintendo 64 (N64)",
            "consigla": "n64",
            "curto": "castlelod"
        },
        {
            "nome": "Hercules: The Legendary Journeys",
            "tags": "Hercules: The Legendary Journeys H칠rcules: A Lend치ria Jornada hercules da serie n64 nintendo 64",
            "console": "Nintendo 64 (N64)",
            "consigla": "n64",
            "curto": "hercules"
        },
        {
            "nome": "Tarzan",
            "tags": "Disney's Tarzan n64 nintendo 64",
            "console": "Nintendo 64 (N64)",
            "consigla": "n64",
            "curto": "tarzan"
        },
        {
            "nome": "Cruis'n Exotica",
            "tags": "Cruis'n Exotica n64 nintendo 64",
            "console": "Nintendo 64 (N64)",
            "consigla": "n64",
            "curto": "exotica"
        },
        {
            "nome": "God of War",
            "tags": "God of War God of War 1 deus da guerra 1 bom de guerra 1 sony ps2 playstation 2",
            "console": "PlayStation 2 (PS2)",
            "consigla": "ps2",
            "curto": "gow1"
        },
        {
            "nome": "Red Dead Revolver",
            "tags": "Red Dead Revolver red dead redemption sony ps2 playstation 2",
            "console": "PlayStation 2 (PS2)",
            "consigla": "ps2",
            "curto": "revolver"
        },
        {
            "nome": "Cars",
            "tags": "Cars carros sony ps2 playstation 2",
            "console": "PlayStation 2 (PS2)",
            "consigla": "ps2",
            "curto": "cars"
        },
        {
            "nome": "Call of Duty - Finest Hour",
            "tags": "Call of Duty Finest Hour cod sony ps2 playstation 2",
            "console": "PlayStation 2 (PS2)",
            "consigla": "ps2",
            "curto": "finest"
        },
        {
            "nome": "Call of Duty 2 - Big Red One",
            "tags": "Call of Duty 2 Big Red One COD 2 Big Red One sony ps2 playstation 2",
            "console": "PlayStation 2 (PS2)",
            "consigla": "ps2",
            "curto": "bigred"
        },
        {
            "nome": "Sonic The Hedgehog 2",
            "tags": "Sonic The Hedgehog 2 Sonic 2 sega mega drive sega genesis",
            "console": "Mega Drive (MD)",
            "consigla": "md",
            "curto": "sonic2"
        },
        {
            "nome": "Sonic The Hedgehog 3 & Knuckles",
            "tags": "Sonic The Hedgehog 3 & Knuckles Sonic 3 & Knuckles Sonic The Hedgehog 3 e Knuckles Sonic 3 e Knuckles Sonic 3K sega mega drive sega genesis",
            "console": "Mega Drive (MD)",
            "consigla": "md",
            "curto": "sonic3k"
        },
        {
            "nome": "God of War II",
            "tags": "God of War II God of War 2 deus da guerra 2 bom de guerra 2 sony ps2 playstation 2",
            "console": "PlayStation 2 (PS2)",
            "consigla": "ps2",
            "curto": "gow2"
        },
        {
            "nome": "Call of Duty World at War Final Fronts",
            "tags": "Call of Duty World at War Final Fronts cod guerra sony ps2 playstation 2",
            "console": "PlayStation 2 (PS2)",
            "consigla": "ps2",
            "curto": "fronts"
        },
        {
            "nome": "Sonic Adventure",
            "tags": "Sonic Adventure sega dc sega dreamcast",
            "console": "Dreamcast (DC)",
            "consigla": "dc",
            "curto": "sonicadv"
        },
        {
            "nome": "Shadow of the Colossus",
            "tags": "Shadow of the Colossus sony ps2 playstation 2",
            "console": "PlayStation 2 (PS2)",
            "consigla": "ps2",
            "curto": "colossus"
        },
        {
            "nome": "Pandemonium",
            "tags": "Pandemonium 1 p칚o dem칪nio 1 sony ps1 playstation 1",
            "console": "PlayStation 1 (PS1)",
            "consigla": "ps1",
            "curto": "pandemonium"
        },
        {
            "nome": "Manhunt",
            "tags": "Manhunt ca칞a homem sony ps2 playstation 2",
            "console": "PlayStation 2 (PS2)",
            "consigla": "ps2",
            "curto": "manhunt1"
        },
        {
            "nome": "Road & Track Presents: The Need for Speed",
            "tags": "Road & Track Presents: The Need for Speed the nfs sony ps1 playstation 1",
            "console": "PlayStation 1 (PS1)",
            "consigla": "ps1",
            "curto": "thenfs"
        },
        {
            "nome": "Sonic Adventure 2",
            "tags": "Sonic Adventure 2 sega dc sega dreamcast",
            "console": "Dreamcast (DC)",
            "consigla": "dc",
            "curto": "sonicadv2"
        },
        {
            "nome": "The Nightmare Before Christmas: Oogie's Revenge",
            "tags": "Tim Burton's The Nightmare Before Christmas: Oogie's Revenge O Estranho Mundo de Jack Tim Burton sony ps2 playstation 2",
            "console": "PlayStation 2 (PS2)",
            "consigla": "ps2",
            "curto": "nbxmas"
        },
        {
            "nome": "Grand Theft Auto III",
            "tags": "Grand Theft Auto III gta iii gta 3 sony ps2 playstation 2",
            "console": "PlayStation 2 (PS2)",
            "consigla": "ps2",
            "curto": "gta3"
        },
        {
            "nome": "Shadow the Hedgehog",
            "tags": "Shadow the Hedgehog sega sony ps2 playstation 2",
            "console": "PlayStation 2 (PS2)",
            "consigla": "ps2",
            "curto": "shadow"
        },
        {
            "nome": "The Sims",
            "tags": "The Sims sony ps2 playstation 2",
            "console": "PlayStation 2 (PS2)",
            "consigla": "ps2",
            "curto": "sims"
        },
        {
            "nome": "Killzone",
            "tags": "Killzone sony ps2 playstation 2",
            "console": "PlayStation 2 (PS2)",
            "consigla": "ps2",
            "curto": "killzone"
        },
        {
            "nome": "Banjo-Kazooie: Grunty's Revenge",
            "tags": "Banjo-Kazooie: Grunty's Revenge banjo kazooie gba banjo gba rare nintendo game boy advance gba",
            "console": "Game Boy Advance (GBA)",
            "consigla": "gba",
            "curto": "banjogrunty"
        },
        {
            "nome": "Grand Theft Auto: Vice City",
            "tags": "Grand Theft Auto: Vice City gta vice city sony ps2 playstation 2",
            "console": "PlayStation 2 (PS2)",
            "consigla": "ps2",
            "curto": "gtavc"
        },
        {
            "nome": "Black",
            "tags": "Black sony ps2 playstation 2",
            "console": "PlayStation 2 (PS2)",
            "consigla": "ps2",
            "curto": "black"
        },
        {
            "nome": "Scarface: The World Is Yours",
            "tags": "Scarface: The World Is Yours sony ps2 playstation 2",
            "console": "PlayStation 2 (PS2)",
            "consigla": "ps2",
            "curto": "scarface"
        },
        {
            "nome": "Super Mario Bros.",
            "tags": "Super Mario Bros. mario 1 nes nintendo",
            "console": "Nintendo (NES)",
            "consigla": "nes",
            "curto": "mario1"
        },
        {
            "nome": "Disney's Lilo & Stitch: Trouble in Paradise",
            "tags": "Disney's Lilo & Stitch: Trouble in Paradise lilo e stitch sony ps1 playstation 1",
            "console": "PlayStation 1 (PS1)",
            "consigla": "ps1",
            "curto": "lilo"
        },
        {
            "nome": "Harry Potter and the Philosopher's Stone",
            "tags": "Harry Potter and the Philosopher's Stone Harry Potter e a Pedra Filosofal sony ps1 playstation 1",
            "console": "PlayStation 1 (PS1)",
            "consigla": "ps1",
            "curto": "harry"
        },
        {
            "nome": "Need for Speed II",
            "tags": "Need for Speed II Need for Speed 2 nfs 2 sony ps1 playstation 1",
            "console": "PlayStation 1 (PS1)",
            "consigla": "ps1",
            "curto": "nfs2"
        },
        {
            "nome": "Harry Potter and the Philosopher's Stone",
            "tags": "Harry Potter and the Philosopher's Stone Harry Potter e a Pedra Filosofal sony ps2 playstation 2",
            "console": "PlayStation 2 (PS2)",
            "consigla": "ps2",
            "curto": "harry"
        },
        {
            "nome": "Pandemonium 2",
            "tags": "Pandemonium 2 p칚o dem칪nio 2 sony ps1 playstation 1",
            "console": "PlayStation 1 (PS1)",
            "consigla": "ps1",
            "curto": "pandemonium2"
        },
        {
            "nome": "Alien Trilogy",
            "tags": "Alien Trilogy sony ps1 playstation 1",
            "console": "PlayStation 1 (PS1)",
            "consigla": "ps1",
            "curto": "alientri"
        },
        {
            "nome": "The Suffering",
            "tags": "The Suffering sofrimento xibiu sony ps2 playstation 2",
            "console": "PlayStation 2 (PS2)",
            "consigla": "ps2",
            "curto": "suffering"
        },
        {
            "nome": "Castlevania: Symphony of the Night",
            "tags": "Castlevania: Symphony of the Night akumajo dracula akumajou dracula akumajyo dracula akumajo dorakyura akumajou dorakyura akumajyo dorakyura sinfonia da noite metroidvania alucard sony ps1 playstation 1",
            "console": "PlayStation 1 (PS1)",
            "consigla": "ps1",
            "curto": "symphony"
        },
        {
            "nome": "Half-Life",
            "tags": "Half-Life half life 1 valve sony ps2 playstation 2",
            "console": "PlayStation 2 (PS2)",
            "consigla": "ps2",
            "curto": "hl1"
        },
        {
            "nome": "Kirby: Nightmare in Dream Land",
            "tags": "Kirby: Nightmare in Dream Land nintendo game boy advance gba",
            "console": "Game Boy Advance (GBA)",
            "consigla": "gba",
            "curto": "kirbynightmare"
        },
        {
            "nome": "Harry Potter and the Chamber of Secrets",
            "tags": "Harry Potter and the Chamber of Secrets Harry Potter e a C칙mara Secreta sony ps2 playstation 2",
            "console": "PlayStation 2 (PS2)",
            "consigla": "ps2",
            "curto": "harrycamara"
        },
        {
            "nome": "The Godfather: The Game",
            "tags": "The Godfather: The Game o poderoso chef칚o o jogo sony ps2 playstation 2",
            "console": "PlayStation 2 (PS2)",
            "consigla": "ps2",
            "curto": "godfather"
        }
    ],
    "standalone": [
        {
            "nome": "ESCONDI ISSO TEMPO DEMAIS - Subway Surfers",
            "tags": "ESCONDI ISSO TEMPO DEMAIS - Subway Surfers coco",
            "imagem": "coco.jpg",
            "consigla": "etc",
            "curto": "coco",
            "link": "https://drive.google.com/file/d/13GLcHstrwxP5MjyujZT2BthBPxgwM38i/view",
            "linkyt": "https://youtu.be/RDhv4UDwxYQ",
            "duracao": {
                "horas": 0,
                "minutos": 5,
                "segundos": 25
            },
            "plataforma": "youtube"
        },
        {
            "nome": "Sarrada do MarceloSouzaF",
            "tags": "Sarrada do MarceloSouzaF meme edit edi칞칚o",
            "imagem": "sarrada.jpg",
            "consigla": "etc",
            "curto": "sarrada",
            "link": "https://drive.google.com/file/d/1-hQwm0_COi97Jc0t_BSqKcPPL2_sCzcq/view",
            "_link": "https://archive.org/details/sarrada-do-marcelosouzaf",
            "linkyt": "",
            "duracao": {
                "horas": 0,
                "minutos": 0,
                "segundos": 57
            },
            "plataforma": "gdrive"
        },
        {
            "nome": "Passeio de Bike pelo Parque Malwee em 2020",
            "tags": "Passeio de Bike pelo Parque Malwee em 2020",
            "imagem": "bike2020.jpg",
            "consigla": "etc",
            "curto": "bike2020",
            "link": "https://drive.google.com/file/d/13T0Vd5avB7rTIxq2Lu9u2LJO21mB4RF3/view",
            "linkyt": "https://youtu.be/E6WVbb-Wwlg",
            "duracao": {
                "horas": 0,
                "minutos": 4,
                "segundos": 0
            },
            "plataforma": "youtube"
        },
        {
            "nome": "Testando Layout para Gameplays de PlayStation 1",
            "tags": "Testando Layout para Gameplays de PlayStation 1 spongebob bob esponja ps1 psx",
            "imagem": "layout.jpg",
            "consigla": "etc",
            "curto": "layout",
            "link": "https://drive.google.com/file/d/1T1eQI-25GnMSNYXU98AwS49-7sCrqQ9e/view",
            "linkyt": "https://youtu.be/RbITng3g_vE",
            "duracao": {
                "horas": 0,
                "minutos": 25,
                "segundos": 37
            },
            "plataforma": "youtube"
        },
        {
            "nome": "2 Anos do Canal na COSTV",
            "tags": "2 Anos do Canal na COSTV",
            "imagem": "2anos_costv.jpg",
            "consigla": "etc",
            "curto": "2anos_costv",
            "link": "",
            "linkyt": "https://youtu.be/3gsj4oeMmtE",
            "duracao": {
                "horas": 0,
                "minutos": 10,
                "segundos": 50
            },
            "plataforma": "youtube",
            "data": "03/01/2022"
        },
        {
            "nome": "Terminando o Passe e Recompensas B칪nus da Temporada 3 do Cap칤tulo 3 do Fortnite",
            "tags": "Terminando o Passe e Recompensas B칪nus da Temporada 3 do Cap칤tulo 3 do Fortnite",
            "imagem": "terminando_passe_fortnite3_3.jpg",
            "consigla": "etc",
            "curto": "terminando_passe_fortnite3_3",
            "link": "",
            "linkyt": "https://youtu.be/J0EYmoZIJkU",
            "duracao": {
                "horas": 0,
                "minutos": 2,
                "segundos": 24
            },
            "plataforma": "youtube",
            "data": "13/09/2022"
        },
        {
            "nome": "2 Mil Inscritos no Canal na COSTV",
            "tags": "2 Mil Inscritos no Canal na COSTV",
            "imagem": "2milsubs_costv.jpg",
            "consigla": "etc",
            "curto": "2milsubs_costv",
            "link": "",
            "linkyt": "https://youtu.be/bUQF_fquQ7M",
            "duracao": {
                "horas": 0,
                "minutos": 4,
                "segundos": 18
            },
            "plataforma": "youtube",
            "data": "15/12/2022"
        },
        {
            "nome": "Trailer do Canal 2023",
            "tags": "Trailer do Canal 2023",
            "imagem": "trailer2023.jpg",
            "consigla": "etc",
            "curto": "trailer2023",
            "link": "https://archive.org/details/msf-trailer-do-canal-2023",
            "linkyt": "",
            "duracao": {
                "horas": 0,
                "minutos": 1,
                "segundos": 9
            },
            "plataforma": "archive",
            "data": "23/12/2022"
        },
        {
            "nome": "3 anos do canal na COSTV",
            "tags": "3 anos do canal na COSTV",
            "imagem": "3anos_costv.jpg",
            "consigla": "etc",
            "curto": "3anos_costv",
            "link": "",
            "linkyt": "https://youtu.be/rQPiGTh_ZTQ",
            "duracao": {
                "horas": 0,
                "minutos": 5,
                "segundos": 55
            },
            "plataforma": "youtube",
            "data": "10/01/2023"
        },
        {
            "nome": "Especial do Meu Anivers치rio de 29 Anos | Jogando Cl치ssicos do Canal",
            "tags": "Especial do Meu Anivers치rio de 29 Anos | Jogando Cl치ssicos do Canal",
            "imagem": "especial_29anos.jpg",
            "consigla": "etc",
            "curto": "especial_29anos",
            "link": "https://archive.org/details/especial-do-meu-aniversario-de-29-anos-jogando-classicos-do-canal",
            "linkyt": "",
            "duracao": {
                "horas": 0,
                "minutos": 39,
                "segundos": 33
            },
            "plataforma": "archive",
            "data": "21/02/2023"
        },
        {
            "nome": "Gaming Channel Trailer | #Consensus2023",
            "tags": "Gaming Channel Trailer | #Consensus2023",
            "imagem": "trailer2023_cos.jpg",
            "consigla": "etc",
            "curto": "trailer2023_cos",
            "link": "https://archive.org/details/msf-gaming-channel-trailer-consensus-2023",
            "linkyt": "",
            "duracao": {
                "horas": 0,
                "minutos": 1,
                "segundos": 9
            },
            "plataforma": "archive",
            "data": "26/04/2023"
        },
        {
            "nome": "Feliz Anivers치rio COSTV #4ANOSDECOSTV",
            "tags": "Feliz Anivers치rio COSTV #4ANOSDECOSTV",
            "imagem": "4anos_costv.jpg",
            "consigla": "etc",
            "curto": "4anos_costv",
            "link": "",
            "linkyt": "https://youtu.be/5JuelzTQht4",
            "duracao": {
                "horas": 0,
                "minutos": 0,
                "segundos": 54
            },
            "plataforma": "youtube",
            "data": "17/06/2023"
        },
        {
            "nome": "Era pra ser um novo recorde no Subway Surfers",
            "tags": "Era pra ser um novo recorde no Subway Surfers",
            "imagem": "recordefalhosub.jpg",
            "consigla": "etc",
            "curto": "recordefalhosub",
            "link": "",
            "linkyt": "https://youtu.be/yJDw_T1FUIY",
            "duracao": {
                "horas": 0,
                "minutos": 0,
                "segundos": 45
            },
            "plataforma": "youtube",
            "data": "03/05/2024"
        },
        {
            "nome": "3 MIL INSCRITOS NA COSTV",
            "tags": "3 MIL INSCRITOS NA COSTV",
            "imagem": "3milsubs_costv.png",
            "consigla": "etc",
            "curto": "3milsubs_costv",
            "link": "",
            "linkyt": "https://youtu.be/EV1dbCgHrXY",
            "duracao": {
                "horas": 0,
                "minutos": 5,
                "segundos": 38
            },
            "plataforma": "youtube",
            "data": "09/07/2024"
        },
        {
            "nome": "A MAIOR LIVE DO CANAL - 10 Horas de Dura칞칚o",
            "tags": "A MAIOR LIVE DO CANAL - 10 Horas de Dura칞칚o recorde",
            "imagem": "livegrandona.png",
            "consigla": "etc",
            "curto": "livegrandona",
            "link": "https://drive.google.com/file/d/1FQL6YPA3jEm78vd_F3wM6CzO-MyXm04J/view",
            "linkyt": "",
            "duracao": {
                "horas": 0,
                "minutos": 4,
                "segundos": 9
            },
            "plataforma": "gdrive"
        },
        {
            "nome": "Marcelo reagindo  coment치rios em v칤deo de Subway Money",
            "tags": "Marcelo reagindo  coment치rios em v칤deo de Subway Money Subway Surfers",
            "imagem": "kkkkkkkkk.jpg",
            "consigla": "etc",
            "curto": "kkkkkkkkk",
            "link": "",
            "linkyt": "https://youtu.be/OiCMeA0VREM",
            "duracao": {
                "horas": 0,
                "minutos": 2,
                "segundos": 5
            },
            "plataforma": "youtube"
        },
        {
            "nome": "Marcelo sendo visitado por besouro + Dj Cleiton rasta",
            "tags": "Marcelo sendo visitado por besouro + Dj Cleiton rasta",
            "imagem": "besouro.jpg",
            "consigla": "etc",
            "curto": "besouro",
            "link": "",
            "linkyt": "https://youtu.be/KMGz80arNjQ",
            "duracao": {
                "horas": 0,
                "minutos": 8,
                "segundos": 13
            },
            "plataforma": "youtube"
        },
        {
            "nome": "Fim da maior live do canal (10 Horas)",
            "tags": "Fim da maior live do canal (10 Horas) recorde de maior live",
            "imagem": "maiorliveclipe.jpg",
            "consigla": "etc",
            "curto": "maiorliveclipe",
            "link": "",
            "linkyt": "https://youtu.be/ysesUFblPpw",
            "duracao": {
                "horas": 0,
                "minutos": 2,
                "segundos": 39
            },
            "plataforma": "youtube"
        },
        {
            "nome": "Tentando jogar o melhor jogo de corrida de todos os tempos",
            "tags": "Tentando jogar o melhor jogo de corrida de todos os tempos need for speed most wanted nfs most wanted",
            "imagem": "mostwantedteste.jpg",
            "consigla": "etc",
            "curto": "mostwantedteste",
            "link": "https://drive.google.com/file/d/1QWkoiRKTLcG8zBjQ5liwaCdaPznh-9mh/view",
            "linkyt": "https://youtu.be/LpDp_1i87sE",
            "duracao": {
                "horas": 0,
                "minutos": 28,
                "segundos": 20
            },
            "plataforma": "youtube"
        },
        {
            "nome": "Marcelo conversando sobre jogos da Rockstar",
            "tags": "Marcelo conversando sobre jogos da Rockstar grand theft auto gta red dead revolver red dead redemption",
            "imagem": "rockstarcomp.jpg",
            "consigla": "etc",
            "curto": "rockstarcomp",
            "link": "",
            "linkyt": "https://youtu.be/m4gjIiIMU2Y",
            "duracao": {
                "horas": 0,
                "minutos": 10,
                "segundos": 35
            },
            "plataforma": "youtube"
        },
        {
            "nome": "Gameplay de Killzone 2 no PlayStation 3",
            "tags": "Gameplay de Killzone 2 no PlayStation 3 ps3",
            "imagem": "killzone2gameplay.jpg",
            "consigla": "etc",
            "curto": "killzone2gameplay",
            "link": "https://drive.google.com/file/d/1kzwCbOGnGd1VeJEBRInjgb4nXF9_prUc/view",
            "linkyt": "https://youtu.be/q4OuFcihe9I",
            "duracao": {
                "horas": 0,
                "minutos": 34,
                "segundos": 47
            },
            "plataforma": "youtube"
        },
        {
            "nome": "Testando filtros do emulador",
            "tags": "Testando filtros do emulador shaders retroarch",
            "imagem": "emufiltros.jpg",
            "consigla": "etc",
            "curto": "emufiltros",
            "link": "",
            "linkyt": "https://youtu.be/4P92D3gxZQw",
            "duracao": {
                "horas": 0,
                "minutos": 24,
                "segundos": 18
            },
            "plataforma": "youtube"
        },
        {
            "nome": "游댠 POV: Marcelo Alpha Elite Rizz CEO DA LUCIDEZ Fazendo Looksmaxxing E Farmando Aura MOGGANDO Leitores Elitistas BETA CODED, Professores MID Das Escolas E Zumbis BRAINROT Por Slop De Subway Surfers 游",
            "tags": "游댠 POV: Marcelo Alpha Elite Rizz CEO DA LUCIDEZ Fazendo Looksmaxxing E Farmando Aura MOGGANDO Leitores Elitistas BETA CODED, Professores MID Das Escolas E Zumbis BRAINROT Por Slop De Subway Surfers 游 livros escola intelig칡ncia sigma based",
            "imagem": "moggador.jpg",
            "consigla": "etc",
            "curto": "moggador",
            "link": "",
            "linkyt": "https://youtu.be/I7COFJf3u5U",
            "duracao": {
                "horas": 0,
                "minutos": 27,
                "segundos": 30
            },
            "plataforma": "youtube"
        },
        {
            "nome": "Tech mostrando o ovo dele",
            "tags": "Tech mostrando o ovo dele hitbox",
            "imagem": "ovo.png",
            "consigla": "etc",
            "curto": "ovo",
            "link": "",
            "linkyt": "https://youtu.be/UNsiqLRMA30",
            "duracao": {
                "horas": 0,
                "minutos": 1,
                "segundos": 20
            },
            "plataforma": "youtube"
        },
        {
            "nome": "Existe um Subway Surfers Brainrot?!",
            "tags": "Existe um Subway Surfers Brainrot subway brainrot",
            "imagem": "subwaybrainrot.jpg",
            "consigla": "etc",
            "curto": "subwaybrainrot",
            "link": "https://drive.google.com/file/d/13q9tqcTRD0kRXyr2dZb5tLn00_7MCik7/view",
            "linkyt": "https://youtu.be/cxP7-0IBMtI",
            "duracao": {
                "horas": 0,
                "minutos": 8,
                "segundos": 44
            },
            "plataforma": "youtube"
        },
        {
            "nome": "Mais um Subway Surfers Brainrot",
            "tags": "Mais um Subway Surfers Brainrot subway brainrot",
            "imagem": "subwaybrainrot2.jpg",
            "consigla": "etc",
            "curto": "subwaybrainrot2",
            "link": "https://drive.google.com/file/d/1K30_s5CVmgAzEqXf9BflQoI_YW286fwW/view",
            "linkyt": "https://youtu.be/XhXm4n6TR7s",
            "duracao": {
                "horas": 0,
                "minutos": 8,
                "segundos": 10
            },
            "plataforma": "youtube"
        },
        {
            "nome": "Roleta do Malsebo - 15/10/2025 a 20/10/2025",
            "tags": "Roleta do Malsebo - 15/10/2025 a 20/10/2025 roleta do marcelo cassino malsebobet malsebo bet marcelobet marcelo bet",
            "imagem": "roleta.png",
            "consigla": "etc",
            "curto": "roleta",
            "link": "",
            "linkyt": "https://youtu.be/8lGPfgl3Ppk",
            "duracao": {
                "horas": 4,
                "minutos": 7,
                "segundos": 41
            },
            "plataforma": "youtube"
        },
        {
            "nome": "CAFEZIN DA MANHA",
            "tags": "CAFEZIN DA MANHA",
            "imagem": "cafezin.png",
            "consigla": "etc",
            "curto": "cafezin",
            "link": "https://drive.google.com/file/d/1NsT2FzbVLJ4H9NluTdh4o1wuYEHc3cue/view",
            "linkyt": "",
            "duracao": {
                "horas": 0,
                "minutos": 27,
                "segundos": 19
            },
            "plataforma": "gdrive"
        },
        {
            "nome": "Marcelo ouvindo a m칰sica +99 do Marcos",
            "tags": "Marcelo ouvindo a m칰sica +99 do Marcos +18 proibida",
            "imagem": "musicadomarcos.jpg",
            "consigla": "etc",
            "curto": "musicadomarcos",
            "link": "",
            "linkyt": "https://youtu.be/ZAa5DyLb6Gc",
            "duracao": {
                "horas": 0,
                "minutos": 3,
                "segundos": 45
            },
            "plataforma": "youtube"
        },
        {
            "nome": "游댮 칄 S칍 UM TESTE, N츾O 칄 LIVE REAL OFICIAL",
            "tags": "游댮 칄 S칍 UM TESTE, N츾O 칄 LIVE REAL OFICIAL",
            "imagem": "testeyoutube1.jpg",
            "consigla": "etc",
            "curto": "testeyoutube1",
            "link": "",
            "linkyt": "https://youtu.be/4JvsecUmPJA",
            "duracao": {
                "horas": 0,
                "minutos": 40,
                "segundos": 25
            },
            "plataforma": "youtube"
        },
        {
            "nome": "MAIS UM TESTE, 123 TESTE TESTANDO ALOU",
            "tags": "MAIS UM TESTE, 123 TESTE TESTANDO ALOU",
            "imagem": "testeyoutube2.jpg",
            "consigla": "etc",
            "curto": "testeyoutube2",
            "link": "",
            "linkyt": "https://youtu.be/RtVcZaFjmLc",
            "duracao": {
                "horas": 0,
                "minutos": 31,
                "segundos": 37
            },
            "plataforma": "youtube"
        },
        {
            "nome": "Marcelo explicando motivo da troca de plataforma pras lives",
            "tags": "Marcelo explicando motivo da troca de plataforma pras lives dlive scam dscam china atraso no pagamento drama de marcelosouzaf perdeu tudo morando de aluguel n칚o sobrou nada pro beta n칚o sobrou nada pro betinha n칚o sobra nada pro beta n칚o sobra nada pro betinha",
            "imagem": "dscam.png",
            "consigla": "etc",
            "curto": "dscam",
            "link": "",
            "linkyt": "https://youtu.be/jBAHQ6ukSa4",
            "duracao": {
                "horas": 0,
                "minutos": 15,
                "segundos": 20
            },
            "plataforma": "youtube"
        },
        {
            "nome": "Experimentando 5 Doces Asi치ticos",
            "tags": "Experimentando 5 Doces Asi치ticos",
            "imagem": "5doces.png",
            "consigla": "etc",
            "curto": "5doces",
            "link": "https://drive.google.com/file/d/10iQQxcUZjYKvxbqEhAXwWttLO9-Ml6Wg/view",
            "linkyt": "",
            "duracao": {
                "horas": 0,
                "minutos": 9,
                "segundos": 59
            },
            "plataforma": "gdrive"
        },
        {
            "nome": "Minha Primeira vez jogando no Super Nintendo",
            "tags": "Minha Primeira vez jogando no Super Nintendo",
            "imagem": "1vezsnes.png",
            "consigla": "etc",
            "curto": "1vezsnes",
            "link": "https://drive.google.com/file/d/1sVll-GRmhYGyGc9O1Z5iXoMle4MF85T3/view",
            "linkyt": "",
            "duracao": {
                "horas": 0,
                "minutos": 1,
                "segundos": 48
            },
            "plataforma": "gdrive"
        },
        {
            "nome": "Subway Surfers Polo Norte 2025 est치 INCR칈VEL nesse natal",
            "tags": "Subway Surfers Polo Norte 2025 est치 INCR칈VEL nesse natal ir칪nico",
            "imagem": "polonorte2025.jpg",
            "consigla": "etc",
            "curto": "polonorte2025",
            "link": "https://drive.google.com/file/d/1ManxCIVfKBwsqTurv4vfv5QRLdR5fReZ/view",
            "linkyt": "https://youtu.be/jyZpyCMnlq8",
            "duracao": {
                "horas": 0,
                "minutos": 9,
                "segundos": 59
            },
            "plataforma": "youtube"
        }
    ],
    "outros": [
        {
            "nome": "Lives gravadas (16/03/2023 a 20/04/2023)",
            "tags": "Lives gravadas (16/03/2023 a 20/04/2023) Kartrider Drift Tomb Raider Reloaded Fortnite SSSnaker",
            "imagem": "1.jpg",
            "console": "Outros",
            "consigla": "outros",
            "curto": "marcoabril2023"
        },
        {
            "nome": "Clair Obscur: Expedition 33",
            "tags": "Clair Obscur: Expedition 33 Clipes",
            "imagem": "1.jpg",
            "console": "Outros",
            "consigla": "outros",
            "curto": "expedition33"
        },
        {
            "nome": "Resident Evil 4 Remake",
            "tags": "Resident Evil 4 Remake Clipes re4 re 4 re4 remake re 4 remake",
            "imagem": "1.jpg",
            "console": "Outros",
            "consigla": "outros",
            "curto": "re4remake"
        },
        {
            "nome": "Megazord Power Rangers no Fortnite",
            "tags": "Megazord Power Rangers no Fortnite Clipes",
            "imagem": "1.jpg",
            "console": "Outros",
            "consigla": "outros",
            "curto": "fort-megazord"
        },
        {
            "nome": "Fortnite 2025",
            "tags": "Fortnite 2025 Clipes",
            "imagem": "1.jpg",
            "console": "Outros",
            "consigla": "outros",
            "curto": "fort-2025"
        },
        {
            "nome": "Gear.Club Unlimited 2",
            "tags": "Gear.Club Unlimited 2 Clipes",
            "imagem": "1.jpg",
            "console": "Outros",
            "consigla": "outros",
            "curto": "gearunl2"
        },
        {
            "nome": "Fortnite 2026",
            "tags": "Fortnite 2026 Clipes",
            "imagem": "1.jpg",
            "console": "Outros",
            "consigla": "outros",
            "curto": "fort-2026"
        }
    ],
    "consoles": [
        {
            "nome": "Nintendo (NES)",
            "sigla": "nes"
        },
        {
            "nome": "Nintendo 64 (N64)",
            "sigla": "n64"
        },
        {
            "nome": "Game Boy Advance (GBA)",
            "sigla": "gba"
        },
        {
            "nome": "Mega Drive (MD)",
            "sigla": "md"
        },
        {
            "nome": "Dreamcast (DC)",
            "sigla": "dc"
        },
        {
            "nome": "PlayStation 1 (PS1)",
            "sigla": "ps1"
        },
        {
            "nome": "PlayStation 2 (PS2)",
            "sigla": "ps2"
        }
    ],
    "temas": [
        {
            "nome": "Padr칚o",
            "valor": "default"
        },
        {
            "nome": "Velho",
            "valor": "old"
        },
        {
            "nome": "Dracula",
            "valor": "dracula"
        },
        {
            "nome": "Terminal",
            "valor": "terminal"
        },
        {
            "nome": "Retro",
            "valor": "retro"
        },
        {
            "nome": "Estante",
            "valor": "estante"
        },
        {
            "nome": "Internet Ruim",
            "valor": "netruim"
        },
        {
            "nome": "Neobrutalismo",
            "valor": "neob"
        },
        {
            "nome": "Arredondado",
            "valor": "arredondado"
        },
        {
            "nome": "98",
            "valor": "98"
        },
        {
            "nome": "XP",
            "valor": "xp"
        },
        {
            "nome": "7",
            "valor": "7"
        },
        {
            "nome": "Geo",
            "valor": "geo"
        }
    ]
}
